CHANGES.rst
MANIFEST.in
README.rst
setup.cfg
setup.py
Solgema/__init__.py
Solgema.EnvironmentViewlets.egg-info/PKG-INFO
Solgema.EnvironmentViewlets.egg-info/PKG-INFO~
Solgema.EnvironmentViewlets.egg-info/SOURCES.txt
Solgema.EnvironmentViewlets.egg-info/dependency_links.txt
Solgema.EnvironmentViewlets.egg-info/entry_points.txt
Solgema.EnvironmentViewlets.egg-info/namespace_packages.txt
Solgema.EnvironmentViewlets.egg-info/not-zip-safe
Solgema.EnvironmentViewlets.egg-info/requires.txt
Solgema.EnvironmentViewlets.egg-info/top_level.txt
Solgema/EnvironmentViewlets/README.txt
Solgema/EnvironmentViewlets/__init__.py
Solgema/EnvironmentViewlets/catalog.py
Solgema/EnvironmentViewlets/catalog.zcml
Solgema/EnvironmentViewlets/config.py
Solgema/EnvironmentViewlets/configure.zcml
Solgema/EnvironmentViewlets/content.py
Solgema/EnvironmentViewlets/event.py
Solgema/EnvironmentViewlets/interfaces.py
Solgema/EnvironmentViewlets/menu.py
Solgema/EnvironmentViewlets/migrations.py
Solgema/EnvironmentViewlets/options.py
Solgema/EnvironmentViewlets/out.txt
Solgema/EnvironmentViewlets/profiles.zcml
Solgema/EnvironmentViewlets/setuphandlers.py
Solgema/EnvironmentViewlets/versions.txt
Solgema/EnvironmentViewlets/Extensions/__init__.py
Solgema/EnvironmentViewlets/Extensions/install.py
Solgema/EnvironmentViewlets/browser/__init__.py
Solgema/EnvironmentViewlets/browser/configure.zcml
Solgema/EnvironmentViewlets/browser/content.py
Solgema/EnvironmentViewlets/browser/content.zcml
Solgema/EnvironmentViewlets/browser/stylesheet.py
Solgema/EnvironmentViewlets/browser/sendaspdf/__init__.py
Solgema/EnvironmentViewlets/browser/sendaspdf/configure.zcml
Solgema/EnvironmentViewlets/browser/sendaspdf/sendaspdf.py
Solgema/EnvironmentViewlets/dx/__init__.py
Solgema/EnvironmentViewlets/dx/configure.zcml
Solgema/EnvironmentViewlets/dx/migration.py
Solgema/EnvironmentViewlets/locales/Solgema.EnvironmentViewlets.pot
Solgema/EnvironmentViewlets/locales/update.sh
Solgema/EnvironmentViewlets/locales/en/LC_MESSAGES/Solgema.EnvironmentViewlets.mo
Solgema/EnvironmentViewlets/locales/en/LC_MESSAGES/Solgema.EnvironmentViewlets.po
Solgema/EnvironmentViewlets/locales/fr/LC_MESSAGES/Solgema.EnvironmentViewlets.mo
Solgema/EnvironmentViewlets/locales/fr/LC_MESSAGES/Solgema.EnvironmentViewlets.po
Solgema/EnvironmentViewlets/profiles/default/actions.xml
Solgema/EnvironmentViewlets/profiles/default/browserlayer.xml
Solgema/EnvironmentViewlets/profiles/default/catalog.xml
