Metadata-Version: 1.1
Name: Solgema.EnvironmentViewlets
Version: 0.6
Summary: Solgema EnvironmentViewlets
Home-page: http://www.martronic.ch/plone_products/Solgema.EnvironmentViewlets
Author: Martronic SA
Author-email: martronic@martronic.ch
License: GPL
Keywords: Solgema
Platform: UNKNOWN
Classifier: Framework :: Plone
Classifier: Programming Language :: Python
Classifier: Topic :: Software Development :: Libraries :: Python Modules
